netic/__init__.py
netic/__main__.py
netic/cli.py
netic/client.py
netic/config.py
netic-0.1.0.dist-info/METADATA
netic-0.1.0.dist-info/WHEEL
netic-0.1.0.dist-info/entry_points.txt
netic-0.1.0.dist-info/top_level.txt
netic-0.1.0.dist-info/RECORD
