Metadata-Version: 2.4
Name: netic
Version: 0.1.0
Summary: CLI Netic
Requires-Dist: requests
